setup.py
cbdc/__init__.py
cbdc/centroid.py
cbdc/tfidf.py
cbdc/tokendict.py
cbdc/util.py
cbdc/vectors.py
cbdc.egg-info/PKG-INFO
cbdc.egg-info/SOURCES.txt
cbdc.egg-info/dependency_links.txt
cbdc.egg-info/requires.txt
cbdc.egg-info/top_level.txt