Metadata-Version: 1.1
Name: cbdc
Version: 0.1.dev225590602
Summary: Centroid-Based Document Classification
Home-page: https://gitlab.informatik.uni-bremen.de/sliedtke/cbdc
Author: Simon Liedtke
Author-email: sliedtke@uni-bremen.de
License: UNKNOWN
Platform: UNKNOWN
Classifier: Development Status :: 3 - Alpha
Classifier: Programming Language :: Python :: 3
Classifier: Programming Language :: Python :: 3.4
Classifier: Topic :: Text Processing
